{
  "_format": "hh-sol-cache-2",
  "files": {
    "/Users/marcuspang/Desktop/Personal/radar-contracts/src/RadarEditions.sol": {
      "lastModificationDate": 1701187355774,
      "contentHash": "dd5ac7070e9382a8516ce331ade2ce7b",
      "sourceName": "src/RadarEditions.sol",
      "solcConfig": {
        "version": "0.8.19",
        "settings": {
          "optimizer": {
            "enabled": true,
            "runs": 200
          },
          "outputSelection": {
            "*": {
              "*": [
                "abi",
                "evm.bytecode",
                "evm.deployedBytecode",
                "evm.methodIdentifiers",
                "metadata",
                "storageLayout"
              ],
              "": [
                "ast"
              ]
            }
          },
          "remappings": [
            "ds-test/=lib/forge-std/lib/ds-test/src/",
            "erc4626-tests/=lib/openzeppelin-contracts/lib/erc4626-tests/",
            "forge-std/=lib/forge-std/src/",
            "@openzeppelin/contracts-upgradeable/=lib/openzeppelin-contracts-upgradeable/contracts/",
            "@openzeppelin/contracts/=lib/openzeppelin-contracts/contracts/",
            "ERC721A-Upgradeable/=lib/ERC721A-Upgradeable/contracts/",
            "openzeppelin-contracts-upgradeable/=lib/openzeppelin-contracts-upgradeable/",
            "openzeppelin-contracts/=lib/openzeppelin-contracts/",
            "openzeppelin/=lib/openzeppelin-contracts-upgradeable/contracts/"
          ]
        }
      },
      "imports": [
        "@openzeppelin/contracts/utils/Strings.sol",
        "./Beliefs/Beliefs.sol",
        "./Editions/EditionsRoles.sol",
        "./IRadarEditions.sol",
        "./Editions/EditionsStructs.sol"
      ],
      "versionPragmas": [
        "^0.8.13"
      ],
      "artifacts": [
        "RadarEditions"
      ]
    },
    "/Users/marcuspang/Desktop/Personal/radar-contracts/src/IRadarEditions.sol": {
      "lastModificationDate": 1697091123180,
      "contentHash": "81eab0fae60eeceb2d83a69a9af240b3",
      "sourceName": "src/IRadarEditions.sol",
      "solcConfig": {
        "version": "0.8.19",
        "settings": {
          "optimizer": {
            "enabled": true,
            "runs": 200
          },
          "outputSelection": {
            "*": {
              "*": [
                "abi",
                "evm.bytecode",
                "evm.deployedBytecode",
                "evm.methodIdentifiers",
                "metadata",
                "storageLayout"
              ],
              "": [
                "ast"
              ]
            }
          },
          "remappings": [
            "ds-test/=lib/forge-std/lib/ds-test/src/",
            "erc4626-tests/=lib/openzeppelin-contracts/lib/erc4626-tests/",
            "forge-std/=lib/forge-std/src/",
            "@openzeppelin/contracts-upgradeable/=lib/openzeppelin-contracts-upgradeable/contracts/",
            "@openzeppelin/contracts/=lib/openzeppelin-contracts/contracts/",
            "ERC721A-Upgradeable/=lib/ERC721A-Upgradeable/contracts/",
            "openzeppelin-contracts-upgradeable/=lib/openzeppelin-contracts-upgradeable/",
            "openzeppelin-contracts/=lib/openzeppelin-contracts/",
            "openzeppelin/=lib/openzeppelin-contracts-upgradeable/contracts/"
          ]
        }
      },
      "imports": [
        "./Editions/EditionsStructs.sol",
        "./Editions/EditionsRoles.sol",
        "./Editions/IEditions.sol",
        "./Beliefs/IBeliefs.sol"
      ],
      "versionPragmas": [
        "^0.8.13"
      ],
      "artifacts": [
        "IRadarEditions"
      ]
    },
    "/Users/marcuspang/Desktop/Personal/radar-contracts/lib/openzeppelin-contracts-upgradeable/contracts/security/PausableUpgradeable.sol": {
      "lastModificationDate": 1691019102258,
      "contentHash": "cbe53d6b803c1102081e00b3a0418ea3",
      "sourceName": "lib/openzeppelin-contracts-upgradeable/contracts/security/PausableUpgradeable.sol",
      "solcConfig": {
        "version": "0.8.19",
        "settings": {
          "optimizer": {
            "enabled": true,
            "runs": 200
          },
          "outputSelection": {
            "*": {
              "*": [
                "abi",
                "evm.bytecode",
                "evm.deployedBytecode",
                "evm.methodIdentifiers",
                "metadata",
                "storageLayout"
              ],
              "": [
                "ast"
              ]
            }
          },
          "remappings": [
            "ds-test/=lib/forge-std/lib/ds-test/src/",
            "erc4626-tests/=lib/openzeppelin-contracts/lib/erc4626-tests/",
            "forge-std/=lib/forge-std/src/",
            "@openzeppelin/contracts-upgradeable/=lib/openzeppelin-contracts-upgradeable/contracts/",
            "@openzeppelin/contracts/=lib/openzeppelin-contracts/contracts/",
            "ERC721A-Upgradeable/=lib/ERC721A-Upgradeable/contracts/",
            "openzeppelin-contracts-upgradeable/=lib/openzeppelin-contracts-upgradeable/",
            "openzeppelin-contracts/=lib/openzeppelin-contracts/",
            "openzeppelin/=lib/openzeppelin-contracts-upgradeable/contracts/"
          ]
        }
      },
      "imports": [
        "../utils/ContextUpgradeable.sol",
        "../proxy/utils/Initializable.sol"
      ],
      "versionPragmas": [
        "^0.8.0"
      ],
      "artifacts": [
        "PausableUpgradeable"
      ]
    },
    "/Users/marcuspang/Desktop/Personal/radar-contracts/lib/openzeppelin-contracts-upgradeable/contracts/access/AccessControlUpgradeable.sol": {
      "lastModificationDate": 1691019102220,
      "contentHash": "c88845618a815ef601f3f552c99d7ebb",
      "sourceName": "lib/openzeppelin-contracts-upgradeable/contracts/access/AccessControlUpgradeable.sol",
      "solcConfig": {
        "version": "0.8.19",
        "settings": {
          "optimizer": {
            "enabled": true,
            "runs": 200
          },
          "outputSelection": {
            "*": {
              "*": [
                "abi",
                "evm.bytecode",
                "evm.deployedBytecode",
                "evm.methodIdentifiers",
                "metadata",
                "storageLayout"
              ],
              "": [
                "ast"
              ]
            }
          },
          "remappings": [
            "ds-test/=lib/forge-std/lib/ds-test/src/",
            "erc4626-tests/=lib/openzeppelin-contracts/lib/erc4626-tests/",
            "forge-std/=lib/forge-std/src/",
            "@openzeppelin/contracts-upgradeable/=lib/openzeppelin-contracts-upgradeable/contracts/",
            "@openzeppelin/contracts/=lib/openzeppelin-contracts/contracts/",
            "ERC721A-Upgradeable/=lib/ERC721A-Upgradeable/contracts/",
            "openzeppelin-contracts-upgradeable/=lib/openzeppelin-contracts-upgradeable/",
            "openzeppelin-contracts/=lib/openzeppelin-contracts/",
            "openzeppelin/=lib/openzeppelin-contracts-upgradeable/contracts/"
          ]
        }
      },
      "imports": [
        "./IAccessControlUpgradeable.sol",
        "../utils/ContextUpgradeable.sol",
        "../utils/StringsUpgradeable.sol",
        "../utils/introspection/ERC165Upgradeable.sol",
        "../proxy/utils/Initializable.sol"
      ],
      "versionPragmas": [
        "^0.8.0"
      ],
      "artifacts": [
        "AccessControlUpgradeable"
      ]
    },
    "/Users/marcuspang/Desktop/Personal/radar-contracts/lib/openzeppelin-contracts/contracts/utils/Strings.sol": {
      "lastModificationDate": 1691019093925,
      "contentHash": "48686fc32a22a3754b8e63321857dd2a",
      "sourceName": "lib/openzeppelin-contracts/contracts/utils/Strings.sol",
      "solcConfig": {
        "version": "0.8.19",
        "settings": {
          "optimizer": {
            "enabled": true,
            "runs": 200
          },
          "outputSelection": {
            "*": {
              "*": [
                "abi",
                "evm.bytecode",
                "evm.deployedBytecode",
                "evm.methodIdentifiers",
                "metadata",
                "storageLayout"
              ],
              "": [
                "ast"
              ]
            }
          },
          "remappings": [
            "ds-test/=lib/forge-std/lib/ds-test/src/",
            "erc4626-tests/=lib/openzeppelin-contracts/lib/erc4626-tests/",
            "forge-std/=lib/forge-std/src/",
            "@openzeppelin/contracts-upgradeable/=lib/openzeppelin-contracts-upgradeable/contracts/",
            "@openzeppelin/contracts/=lib/openzeppelin-contracts/contracts/",
            "ERC721A-Upgradeable/=lib/ERC721A-Upgradeable/contracts/",
            "openzeppelin-contracts-upgradeable/=lib/openzeppelin-contracts-upgradeable/",
            "openzeppelin-contracts/=lib/openzeppelin-contracts/",
            "openzeppelin/=lib/openzeppelin-contracts-upgradeable/contracts/"
          ]
        }
      },
      "imports": [
        "./math/Math.sol",
        "./math/SignedMath.sol"
      ],
      "versionPragmas": [
        "^0.8.0"
      ],
      "artifacts": [
        "Strings"
      ]
    },
    "/Users/marcuspang/Desktop/Personal/radar-contracts/lib/openzeppelin-contracts-upgradeable/contracts/proxy/utils/Initializable.sol": {
      "lastModificationDate": 1691019102257,
      "contentHash": "b0970a564d121abf9adfff8d1a01eb16",
      "sourceName": "lib/openzeppelin-contracts-upgradeable/contracts/proxy/utils/Initializable.sol",
      "solcConfig": {
        "version": "0.8.19",
        "settings": {
          "optimizer": {
            "enabled": true,
            "runs": 200
          },
          "outputSelection": {
            "*": {
              "*": [
                "abi",
                "evm.bytecode",
                "evm.deployedBytecode",
                "evm.methodIdentifiers",
                "metadata",
                "storageLayout"
              ],
              "": [
                "ast"
              ]
            }
          },
          "remappings": [
            "ds-test/=lib/forge-std/lib/ds-test/src/",
            "erc4626-tests/=lib/openzeppelin-contracts/lib/erc4626-tests/",
            "forge-std/=lib/forge-std/src/",
            "@openzeppelin/contracts-upgradeable/=lib/openzeppelin-contracts-upgradeable/contracts/",
            "@openzeppelin/contracts/=lib/openzeppelin-contracts/contracts/",
            "ERC721A-Upgradeable/=lib/ERC721A-Upgradeable/contracts/",
            "openzeppelin-contracts-upgradeable/=lib/openzeppelin-contracts-upgradeable/",
            "openzeppelin-contracts/=lib/openzeppelin-contracts/",
            "openzeppelin/=lib/openzeppelin-contracts-upgradeable/contracts/"
          ]
        }
      },
      "imports": [
        "../../utils/AddressUpgradeable.sol"
      ],
      "versionPragmas": [
        "^0.8.2"
      ],
      "artifacts": [
        "Initializable"
      ]
    },
    "/Users/marcuspang/Desktop/Personal/radar-contracts/lib/openzeppelin-contracts-upgradeable/contracts/token/ERC1155/ERC1155Upgradeable.sol": {
      "lastModificationDate": 1691019102259,
      "contentHash": "5187bf78bbb054d9d4f5121232d5398b",
      "sourceName": "lib/openzeppelin-contracts-upgradeable/contracts/token/ERC1155/ERC1155Upgradeable.sol",
      "solcConfig": {
        "version": "0.8.19",
        "settings": {
          "optimizer": {
            "enabled": true,
            "runs": 200
          },
          "outputSelection": {
            "*": {
              "*": [
                "abi",
                "evm.bytecode",
                "evm.deployedBytecode",
                "evm.methodIdentifiers",
                "metadata",
                "storageLayout"
              ],
              "": [
                "ast"
              ]
            }
          },
          "remappings": [
            "ds-test/=lib/forge-std/lib/ds-test/src/",
            "erc4626-tests/=lib/openzeppelin-contracts/lib/erc4626-tests/",
            "forge-std/=lib/forge-std/src/",
            "@openzeppelin/contracts-upgradeable/=lib/openzeppelin-contracts-upgradeable/contracts/",
            "@openzeppelin/contracts/=lib/openzeppelin-contracts/contracts/",
            "ERC721A-Upgradeable/=lib/ERC721A-Upgradeable/contracts/",
            "openzeppelin-contracts-upgradeable/=lib/openzeppelin-contracts-upgradeable/",
            "openzeppelin-contracts/=lib/openzeppelin-contracts/",
            "openzeppelin/=lib/openzeppelin-contracts-upgradeable/contracts/"
          ]
        }
      },
      "imports": [
        "./IERC1155Upgradeable.sol",
        "./IERC1155ReceiverUpgradeable.sol",
        "./extensions/IERC1155MetadataURIUpgradeable.sol",
        "../../utils/AddressUpgradeable.sol",
        "../../utils/ContextUpgradeable.sol",
        "../../utils/introspection/ERC165Upgradeable.sol",
        "../../proxy/utils/Initializable.sol"
      ],
      "versionPragmas": [
        "^0.8.0"
      ],
      "artifacts": [
        "ERC1155Upgradeable"
      ]
    },
    "/Users/marcuspang/Desktop/Personal/radar-contracts/lib/openzeppelin-contracts-upgradeable/contracts/proxy/utils/UUPSUpgradeable.sol": {
      "lastModificationDate": 1691019102257,
      "contentHash": "52ef5d6c909d6f8ef3077445d3328eca",
      "sourceName": "lib/openzeppelin-contracts-upgradeable/contracts/proxy/utils/UUPSUpgradeable.sol",
      "solcConfig": {
        "version": "0.8.19",
        "settings": {
          "optimizer": {
            "enabled": true,
            "runs": 200
          },
          "outputSelection": {
            "*": {
              "*": [
                "abi",
                "evm.bytecode",
                "evm.deployedBytecode",
                "evm.methodIdentifiers",
                "metadata",
                "storageLayout"
              ],
              "": [
                "ast"
              ]
            }
          },
          "remappings": [
            "ds-test/=lib/forge-std/lib/ds-test/src/",
            "erc4626-tests/=lib/openzeppelin-contracts/lib/erc4626-tests/",
            "forge-std/=lib/forge-std/src/",
            "@openzeppelin/contracts-upgradeable/=lib/openzeppelin-contracts-upgradeable/contracts/",
            "@openzeppelin/contracts/=lib/openzeppelin-contracts/contracts/",
            "ERC721A-Upgradeable/=lib/ERC721A-Upgradeable/contracts/",
            "openzeppelin-contracts-upgradeable/=lib/openzeppelin-contracts-upgradeable/",
            "openzeppelin-contracts/=lib/openzeppelin-contracts/",
            "openzeppelin/=lib/openzeppelin-contracts-upgradeable/contracts/"
          ]
        }
      },
      "imports": [
        "../../interfaces/draft-IERC1822Upgradeable.sol",
        "../ERC1967/ERC1967UpgradeUpgradeable.sol",
        "./Initializable.sol"
      ],
      "versionPragmas": [
        "^0.8.0"
      ],
      "artifacts": [
        "UUPSUpgradeable"
      ]
    },
    "/Users/marcuspang/Desktop/Personal/radar-contracts/lib/openzeppelin-contracts-upgradeable/contracts/token/ERC1155/extensions/ERC1155BurnableUpgradeable.sol": {
      "lastModificationDate": 1691019102259,
      "contentHash": "fff2ea78a61d6bb81a90a28e62309608",
      "sourceName": "lib/openzeppelin-contracts-upgradeable/contracts/token/ERC1155/extensions/ERC1155BurnableUpgradeable.sol",
      "solcConfig": {
        "version": "0.8.19",
        "settings": {
          "optimizer": {
            "enabled": true,
            "runs": 200
          },
          "outputSelection": {
            "*": {
              "*": [
                "abi",
                "evm.bytecode",
                "evm.deployedBytecode",
                "evm.methodIdentifiers",
                "metadata",
                "storageLayout"
              ],
              "": [
                "ast"
              ]
            }
          },
          "remappings": [
            "ds-test/=lib/forge-std/lib/ds-test/src/",
            "erc4626-tests/=lib/openzeppelin-contracts/lib/erc4626-tests/",
            "forge-std/=lib/forge-std/src/",
            "@openzeppelin/contracts-upgradeable/=lib/openzeppelin-contracts-upgradeable/contracts/",
            "@openzeppelin/contracts/=lib/openzeppelin-contracts/contracts/",
            "ERC721A-Upgradeable/=lib/ERC721A-Upgradeable/contracts/",
            "openzeppelin-contracts-upgradeable/=lib/openzeppelin-contracts-upgradeable/",
            "openzeppelin-contracts/=lib/openzeppelin-contracts/",
            "openzeppelin/=lib/openzeppelin-contracts-upgradeable/contracts/"
          ]
        }
      },
      "imports": [
        "../ERC1155Upgradeable.sol",
        "../../../proxy/utils/Initializable.sol"
      ],
      "versionPragmas": [
        "^0.8.0"
      ],
      "artifacts": [
        "ERC1155BurnableUpgradeable"
      ]
    },
    "/Users/marcuspang/Desktop/Personal/radar-contracts/lib/openzeppelin-contracts/contracts/utils/structs/BitMaps.sol": {
      "lastModificationDate": 1691019093930,
      "contentHash": "8961863c7c3748012c849e980477582c",
      "sourceName": "lib/openzeppelin-contracts/contracts/utils/structs/BitMaps.sol",
      "solcConfig": {
        "version": "0.8.19",
        "settings": {
          "optimizer": {
            "enabled": true,
            "runs": 200
          },
          "outputSelection": {
            "*": {
              "*": [
                "abi",
                "evm.bytecode",
                "evm.deployedBytecode",
                "evm.methodIdentifiers",
                "metadata",
                "storageLayout"
              ],
              "": [
                "ast"
              ]
            }
          },
          "remappings": [
            "ds-test/=lib/forge-std/lib/ds-test/src/",
            "erc4626-tests/=lib/openzeppelin-contracts/lib/erc4626-tests/",
            "forge-std/=lib/forge-std/src/",
            "@openzeppelin/contracts-upgradeable/=lib/openzeppelin-contracts-upgradeable/contracts/",
            "@openzeppelin/contracts/=lib/openzeppelin-contracts/contracts/",
            "ERC721A-Upgradeable/=lib/ERC721A-Upgradeable/contracts/",
            "openzeppelin-contracts-upgradeable/=lib/openzeppelin-contracts-upgradeable/",
            "openzeppelin-contracts/=lib/openzeppelin-contracts/",
            "openzeppelin/=lib/openzeppelin-contracts-upgradeable/contracts/"
          ]
        }
      },
      "imports": [],
      "versionPragmas": [
        "^0.8.0"
      ],
      "artifacts": [
        "BitMaps"
      ]
    },
    "/Users/marcuspang/Desktop/Personal/radar-contracts/lib/openzeppelin-contracts-upgradeable/contracts/token/ERC1155/extensions/ERC1155SupplyUpgradeable.sol": {
      "lastModificationDate": 1691019102260,
      "contentHash": "fbf5fdb7a74554410a3b4059f3d314df",
      "sourceName": "lib/openzeppelin-contracts-upgradeable/contracts/token/ERC1155/extensions/ERC1155SupplyUpgradeable.sol",
      "solcConfig": {
        "version": "0.8.19",
        "settings": {
          "optimizer": {
            "enabled": true,
            "runs": 200
          },
          "outputSelection": {
            "*": {
              "*": [
                "abi",
                "evm.bytecode",
                "evm.deployedBytecode",
                "evm.methodIdentifiers",
                "metadata",
                "storageLayout"
              ],
              "": [
                "ast"
              ]
            }
          },
          "remappings": [
            "ds-test/=lib/forge-std/lib/ds-test/src/",
            "erc4626-tests/=lib/openzeppelin-contracts/lib/erc4626-tests/",
            "forge-std/=lib/forge-std/src/",
            "@openzeppelin/contracts-upgradeable/=lib/openzeppelin-contracts-upgradeable/contracts/",
            "@openzeppelin/contracts/=lib/openzeppelin-contracts/contracts/",
            "ERC721A-Upgradeable/=lib/ERC721A-Upgradeable/contracts/",
            "openzeppelin-contracts-upgradeable/=lib/openzeppelin-contracts-upgradeable/",
            "openzeppelin-contracts/=lib/openzeppelin-contracts/",
            "openzeppelin/=lib/openzeppelin-contracts-upgradeable/contracts/"
          ]
        }
      },
      "imports": [
        "../ERC1155Upgradeable.sol",
        "../../../proxy/utils/Initializable.sol"
      ],
      "versionPragmas": [
        "^0.8.0"
      ],
      "artifacts": [
        "ERC1155SupplyUpgradeable"
      ]
    },
    "/Users/marcuspang/Desktop/Personal/radar-contracts/lib/openzeppelin-contracts-upgradeable/contracts/utils/ContextUpgradeable.sol": {
      "lastModificationDate": 1691019102272,
      "contentHash": "6200b84950eb05b4a92a39fd1d6e0f9b",
      "sourceName": "lib/openzeppelin-contracts-upgradeable/contracts/utils/ContextUpgradeable.sol",
      "solcConfig": {
        "version": "0.8.19",
        "settings": {
          "optimizer": {
            "enabled": true,
            "runs": 200
          },
          "outputSelection": {
            "*": {
              "*": [
                "abi",
                "evm.bytecode",
                "evm.deployedBytecode",
                "evm.methodIdentifiers",
                "metadata",
                "storageLayout"
              ],
              "": [
                "ast"
              ]
            }
          },
          "remappings": [
            "ds-test/=lib/forge-std/lib/ds-test/src/",
            "erc4626-tests/=lib/openzeppelin-contracts/lib/erc4626-tests/",
            "forge-std/=lib/forge-std/src/",
            "@openzeppelin/contracts-upgradeable/=lib/openzeppelin-contracts-upgradeable/contracts/",
            "@openzeppelin/contracts/=lib/openzeppelin-contracts/contracts/",
            "ERC721A-Upgradeable/=lib/ERC721A-Upgradeable/contracts/",
            "openzeppelin-contracts-upgradeable/=lib/openzeppelin-contracts-upgradeable/",
            "openzeppelin-contracts/=lib/openzeppelin-contracts/",
            "openzeppelin/=lib/openzeppelin-contracts-upgradeable/contracts/"
          ]
        }
      },
      "imports": [
        "../proxy/utils/Initializable.sol"
      ],
      "versionPragmas": [
        "^0.8.0"
      ],
      "artifacts": [
        "ContextUpgradeable"
      ]
    },
    "/Users/marcuspang/Desktop/Personal/radar-contracts/lib/openzeppelin-contracts-upgradeable/contracts/utils/AddressUpgradeable.sol": {
      "lastModificationDate": 1691019102271,
      "contentHash": "c30c805386fda8a42ff515da963d3a95",
      "sourceName": "lib/openzeppelin-contracts-upgradeable/contracts/utils/AddressUpgradeable.sol",
      "solcConfig": {
        "version": "0.8.19",
        "settings": {
          "optimizer": {
            "enabled": true,
            "runs": 200
          },
          "outputSelection": {
            "*": {
              "*": [
                "abi",
                "evm.bytecode",
                "evm.deployedBytecode",
                "evm.methodIdentifiers",
                "metadata",
                "storageLayout"
              ],
              "": [
                "ast"
              ]
            }
          },
          "remappings": [
            "ds-test/=lib/forge-std/lib/ds-test/src/",
            "erc4626-tests/=lib/openzeppelin-contracts/lib/erc4626-tests/",
            "forge-std/=lib/forge-std/src/",
            "@openzeppelin/contracts-upgradeable/=lib/openzeppelin-contracts-upgradeable/contracts/",
            "@openzeppelin/contracts/=lib/openzeppelin-contracts/contracts/",
            "ERC721A-Upgradeable/=lib/ERC721A-Upgradeable/contracts/",
            "openzeppelin-contracts-upgradeable/=lib/openzeppelin-contracts-upgradeable/",
            "openzeppelin-contracts/=lib/openzeppelin-contracts/",
            "openzeppelin/=lib/openzeppelin-contracts-upgradeable/contracts/"
          ]
        }
      },
      "imports": [],
      "versionPragmas": [
        "^0.8.1"
      ],
      "artifacts": [
        "AddressUpgradeable"
      ]
    },
    "/Users/marcuspang/Desktop/Personal/radar-contracts/lib/openzeppelin-contracts-upgradeable/contracts/utils/StringsUpgradeable.sol": {
      "lastModificationDate": 1691019102273,
      "contentHash": "c221361be1c4953f5b71f47475b90266",
      "sourceName": "lib/openzeppelin-contracts-upgradeable/contracts/utils/StringsUpgradeable.sol",
      "solcConfig": {
        "version": "0.8.19",
        "settings": {
          "optimizer": {
            "enabled": true,
            "runs": 200
          },
          "outputSelection": {
            "*": {
              "*": [
                "abi",
                "evm.bytecode",
                "evm.deployedBytecode",
                "evm.methodIdentifiers",
                "metadata",
                "storageLayout"
              ],
              "": [
                "ast"
              ]
            }
          },
          "remappings": [
            "ds-test/=lib/forge-std/lib/ds-test/src/",
            "erc4626-tests/=lib/openzeppelin-contracts/lib/erc4626-tests/",
            "forge-std/=lib/forge-std/src/",
            "@openzeppelin/contracts-upgradeable/=lib/openzeppelin-contracts-upgradeable/contracts/",
            "@openzeppelin/contracts/=lib/openzeppelin-contracts/contracts/",
            "ERC721A-Upgradeable/=lib/ERC721A-Upgradeable/contracts/",
            "openzeppelin-contracts-upgradeable/=lib/openzeppelin-contracts-upgradeable/",
            "openzeppelin-contracts/=lib/openzeppelin-contracts/",
            "openzeppelin/=lib/openzeppelin-contracts-upgradeable/contracts/"
          ]
        }
      },
      "imports": [
        "./math/MathUpgradeable.sol",
        "./math/SignedMathUpgradeable.sol"
      ],
      "versionPragmas": [
        "^0.8.0"
      ],
      "artifacts": [
        "StringsUpgradeable"
      ]
    },
    "/Users/marcuspang/Desktop/Personal/radar-contracts/lib/openzeppelin-contracts-upgradeable/contracts/utils/introspection/ERC165Upgradeable.sol": {
      "lastModificationDate": 1691019102276,
      "contentHash": "5f2d8b81c0ff5bd2047b4846c20b998d",
      "sourceName": "lib/openzeppelin-contracts-upgradeable/contracts/utils/introspection/ERC165Upgradeable.sol",
      "solcConfig": {
        "version": "0.8.19",
        "settings": {
          "optimizer": {
            "enabled": true,
            "runs": 200
          },
          "outputSelection": {
            "*": {
              "*": [
                "abi",
                "evm.bytecode",
                "evm.deployedBytecode",
                "evm.methodIdentifiers",
                "metadata",
                "storageLayout"
              ],
              "": [
                "ast"
              ]
            }
          },
          "remappings": [
            "ds-test/=lib/forge-std/lib/ds-test/src/",
            "erc4626-tests/=lib/openzeppelin-contracts/lib/erc4626-tests/",
            "forge-std/=lib/forge-std/src/",
            "@openzeppelin/contracts-upgradeable/=lib/openzeppelin-contracts-upgradeable/contracts/",
            "@openzeppelin/contracts/=lib/openzeppelin-contracts/contracts/",
            "ERC721A-Upgradeable/=lib/ERC721A-Upgradeable/contracts/",
            "openzeppelin-contracts-upgradeable/=lib/openzeppelin-contracts-upgradeable/",
            "openzeppelin-contracts/=lib/openzeppelin-contracts/",
            "openzeppelin/=lib/openzeppelin-contracts-upgradeable/contracts/"
          ]
        }
      },
      "imports": [
        "./IERC165Upgradeable.sol",
        "../../proxy/utils/Initializable.sol"
      ],
      "versionPragmas": [
        "^0.8.0"
      ],
      "artifacts": [
        "ERC165Upgradeable"
      ]
    },
    "/Users/marcuspang/Desktop/Personal/radar-contracts/lib/openzeppelin-contracts-upgradeable/contracts/access/IAccessControlUpgradeable.sol": {
      "lastModificationDate": 1691019102220,
      "contentHash": "21b43d1337ebc77c11da3cbe3fd65316",
      "sourceName": "lib/openzeppelin-contracts-upgradeable/contracts/access/IAccessControlUpgradeable.sol",
      "solcConfig": {
        "version": "0.8.19",
        "settings": {
          "optimizer": {
            "enabled": true,
            "runs": 200
          },
          "outputSelection": {
            "*": {
              "*": [
                "abi",
                "evm.bytecode",
                "evm.deployedBytecode",
                "evm.methodIdentifiers",
                "metadata",
                "storageLayout"
              ],
              "": [
                "ast"
              ]
            }
          },
          "remappings": [
            "ds-test/=lib/forge-std/lib/ds-test/src/",
            "erc4626-tests/=lib/openzeppelin-contracts/lib/erc4626-tests/",
            "forge-std/=lib/forge-std/src/",
            "@openzeppelin/contracts-upgradeable/=lib/openzeppelin-contracts-upgradeable/contracts/",
            "@openzeppelin/contracts/=lib/openzeppelin-contracts/contracts/",
            "ERC721A-Upgradeable/=lib/ERC721A-Upgradeable/contracts/",
            "openzeppelin-contracts-upgradeable/=lib/openzeppelin-contracts-upgradeable/",
            "openzeppelin-contracts/=lib/openzeppelin-contracts/",
            "openzeppelin/=lib/openzeppelin-contracts-upgradeable/contracts/"
          ]
        }
      },
      "imports": [],
      "versionPragmas": [
        "^0.8.0"
      ],
      "artifacts": [
        "IAccessControlUpgradeable"
      ]
    },
    "/Users/marcuspang/Desktop/Personal/radar-contracts/lib/openzeppelin-contracts-upgradeable/contracts/utils/math/MathUpgradeable.sol": {
      "lastModificationDate": 1691019102277,
      "contentHash": "5a2a749b45b6a8eb035f4bf75addcb27",
      "sourceName": "lib/openzeppelin-contracts-upgradeable/contracts/utils/math/MathUpgradeable.sol",
      "solcConfig": {
        "version": "0.8.19",
        "settings": {
          "optimizer": {
            "enabled": true,
            "runs": 200
          },
          "outputSelection": {
            "*": {
              "*": [
                "abi",
                "evm.bytecode",
                "evm.deployedBytecode",
                "evm.methodIdentifiers",
                "metadata",
                "storageLayout"
              ],
              "": [
                "ast"
              ]
            }
          },
          "remappings": [
            "ds-test/=lib/forge-std/lib/ds-test/src/",
            "erc4626-tests/=lib/openzeppelin-contracts/lib/erc4626-tests/",
            "forge-std/=lib/forge-std/src/",
            "@openzeppelin/contracts-upgradeable/=lib/openzeppelin-contracts-upgradeable/contracts/",
            "@openzeppelin/contracts/=lib/openzeppelin-contracts/contracts/",
            "ERC721A-Upgradeable/=lib/ERC721A-Upgradeable/contracts/",
            "openzeppelin-contracts-upgradeable/=lib/openzeppelin-contracts-upgradeable/",
            "openzeppelin-contracts/=lib/openzeppelin-contracts/",
            "openzeppelin/=lib/openzeppelin-contracts-upgradeable/contracts/"
          ]
        }
      },
      "imports": [],
      "versionPragmas": [
        "^0.8.0"
      ],
      "artifacts": [
        "MathUpgradeable"
      ]
    },
    "/Users/marcuspang/Desktop/Personal/radar-contracts/lib/openzeppelin-contracts-upgradeable/contracts/utils/math/SignedMathUpgradeable.sol": {
      "lastModificationDate": 1691019102278,
      "contentHash": "2a6b819b2e241091ada6d645df3e3929",
      "sourceName": "lib/openzeppelin-contracts-upgradeable/contracts/utils/math/SignedMathUpgradeable.sol",
      "solcConfig": {
        "version": "0.8.19",
        "settings": {
          "optimizer": {
            "enabled": true,
            "runs": 200
          },
          "outputSelection": {
            "*": {
              "*": [
                "abi",
                "evm.bytecode",
                "evm.deployedBytecode",
                "evm.methodIdentifiers",
                "metadata",
                "storageLayout"
              ],
              "": [
                "ast"
              ]
            }
          },
          "remappings": [
            "ds-test/=lib/forge-std/lib/ds-test/src/",
            "erc4626-tests/=lib/openzeppelin-contracts/lib/erc4626-tests/",
            "forge-std/=lib/forge-std/src/",
            "@openzeppelin/contracts-upgradeable/=lib/openzeppelin-contracts-upgradeable/contracts/",
            "@openzeppelin/contracts/=lib/openzeppelin-contracts/contracts/",
            "ERC721A-Upgradeable/=lib/ERC721A-Upgradeable/contracts/",
            "openzeppelin-contracts-upgradeable/=lib/openzeppelin-contracts-upgradeable/",
            "openzeppelin-contracts/=lib/openzeppelin-contracts/",
            "openzeppelin/=lib/openzeppelin-contracts-upgradeable/contracts/"
          ]
        }
      },
      "imports": [],
      "versionPragmas": [
        "^0.8.0"
      ],
      "artifacts": [
        "SignedMathUpgradeable"
      ]
    },
    "/Users/marcuspang/Desktop/Personal/radar-contracts/lib/openzeppelin-contracts-upgradeable/contracts/utils/introspection/IERC165Upgradeable.sol": {
      "lastModificationDate": 1691019102276,
      "contentHash": "d6ecf203a5e72c845be9bbf2f304a289",
      "sourceName": "lib/openzeppelin-contracts-upgradeable/contracts/utils/introspection/IERC165Upgradeable.sol",
      "solcConfig": {
        "version": "0.8.19",
        "settings": {
          "optimizer": {
            "enabled": true,
            "runs": 200
          },
          "outputSelection": {
            "*": {
              "*": [
                "abi",
                "evm.bytecode",
                "evm.deployedBytecode",
                "evm.methodIdentifiers",
                "metadata",
                "storageLayout"
              ],
              "": [
                "ast"
              ]
            }
          },
          "remappings": [
            "ds-test/=lib/forge-std/lib/ds-test/src/",
            "erc4626-tests/=lib/openzeppelin-contracts/lib/erc4626-tests/",
            "forge-std/=lib/forge-std/src/",
            "@openzeppelin/contracts-upgradeable/=lib/openzeppelin-contracts-upgradeable/contracts/",
            "@openzeppelin/contracts/=lib/openzeppelin-contracts/contracts/",
            "ERC721A-Upgradeable/=lib/ERC721A-Upgradeable/contracts/",
            "openzeppelin-contracts-upgradeable/=lib/openzeppelin-contracts-upgradeable/",
            "openzeppelin-contracts/=lib/openzeppelin-contracts/",
            "openzeppelin/=lib/openzeppelin-contracts-upgradeable/contracts/"
          ]
        }
      },
      "imports": [],
      "versionPragmas": [
        "^0.8.0"
      ],
      "artifacts": [
        "IERC165Upgradeable"
      ]
    },
    "/Users/marcuspang/Desktop/Personal/radar-contracts/lib/openzeppelin-contracts/contracts/utils/math/Math.sol": {
      "lastModificationDate": 1691019093928,
      "contentHash": "fe63409d8a06818b926cf89e0ea88b1b",
      "sourceName": "lib/openzeppelin-contracts/contracts/utils/math/Math.sol",
      "solcConfig": {
        "version": "0.8.19",
        "settings": {
          "optimizer": {
            "enabled": true,
            "runs": 200
          },
          "outputSelection": {
            "*": {
              "*": [
                "abi",
                "evm.bytecode",
                "evm.deployedBytecode",
                "evm.methodIdentifiers",
                "metadata",
                "storageLayout"
              ],
              "": [
                "ast"
              ]
            }
          },
          "remappings": [
            "ds-test/=lib/forge-std/lib/ds-test/src/",
            "erc4626-tests/=lib/openzeppelin-contracts/lib/erc4626-tests/",
            "forge-std/=lib/forge-std/src/",
            "@openzeppelin/contracts-upgradeable/=lib/openzeppelin-contracts-upgradeable/contracts/",
            "@openzeppelin/contracts/=lib/openzeppelin-contracts/contracts/",
            "ERC721A-Upgradeable/=lib/ERC721A-Upgradeable/contracts/",
            "openzeppelin-contracts-upgradeable/=lib/openzeppelin-contracts-upgradeable/",
            "openzeppelin-contracts/=lib/openzeppelin-contracts/",
            "openzeppelin/=lib/openzeppelin-contracts-upgradeable/contracts/"
          ]
        }
      },
      "imports": [],
      "versionPragmas": [
        "^0.8.0"
      ],
      "artifacts": [
        "Math"
      ]
    },
    "/Users/marcuspang/Desktop/Personal/radar-contracts/lib/openzeppelin-contracts/contracts/utils/math/SignedMath.sol": {
      "lastModificationDate": 1691019093929,
      "contentHash": "9488ebd4daacfee8ad04811600d7d061",
      "sourceName": "lib/openzeppelin-contracts/contracts/utils/math/SignedMath.sol",
      "solcConfig": {
        "version": "0.8.19",
        "settings": {
          "optimizer": {
            "enabled": true,
            "runs": 200
          },
          "outputSelection": {
            "*": {
              "*": [
                "abi",
                "evm.bytecode",
                "evm.deployedBytecode",
                "evm.methodIdentifiers",
                "metadata",
                "storageLayout"
              ],
              "": [
                "ast"
              ]
            }
          },
          "remappings": [
            "ds-test/=lib/forge-std/lib/ds-test/src/",
            "erc4626-tests/=lib/openzeppelin-contracts/lib/erc4626-tests/",
            "forge-std/=lib/forge-std/src/",
            "@openzeppelin/contracts-upgradeable/=lib/openzeppelin-contracts-upgradeable/contracts/",
            "@openzeppelin/contracts/=lib/openzeppelin-contracts/contracts/",
            "ERC721A-Upgradeable/=lib/ERC721A-Upgradeable/contracts/",
            "openzeppelin-contracts-upgradeable/=lib/openzeppelin-contracts-upgradeable/",
            "openzeppelin-contracts/=lib/openzeppelin-contracts/",
            "openzeppelin/=lib/openzeppelin-contracts-upgradeable/contracts/"
          ]
        }
      },
      "imports": [],
      "versionPragmas": [
        "^0.8.0"
      ],
      "artifacts": [
        "SignedMath"
      ]
    },
    "/Users/marcuspang/Desktop/Personal/radar-contracts/lib/openzeppelin-contracts-upgradeable/contracts/token/ERC1155/IERC1155Upgradeable.sol": {
      "lastModificationDate": 1691019102259,
      "contentHash": "5712a8d74dc6ae8d66b65cdfac95846b",
      "sourceName": "lib/openzeppelin-contracts-upgradeable/contracts/token/ERC1155/IERC1155Upgradeable.sol",
      "solcConfig": {
        "version": "0.8.19",
        "settings": {
          "optimizer": {
            "enabled": true,
            "runs": 200
          },
          "outputSelection": {
            "*": {
              "*": [
                "abi",
                "evm.bytecode",
                "evm.deployedBytecode",
                "evm.methodIdentifiers",
                "metadata",
                "storageLayout"
              ],
              "": [
                "ast"
              ]
            }
          },
          "remappings": [
            "ds-test/=lib/forge-std/lib/ds-test/src/",
            "erc4626-tests/=lib/openzeppelin-contracts/lib/erc4626-tests/",
            "forge-std/=lib/forge-std/src/",
            "@openzeppelin/contracts-upgradeable/=lib/openzeppelin-contracts-upgradeable/contracts/",
            "@openzeppelin/contracts/=lib/openzeppelin-contracts/contracts/",
            "ERC721A-Upgradeable/=lib/ERC721A-Upgradeable/contracts/",
            "openzeppelin-contracts-upgradeable/=lib/openzeppelin-contracts-upgradeable/",
            "openzeppelin-contracts/=lib/openzeppelin-contracts/",
            "openzeppelin/=lib/openzeppelin-contracts-upgradeable/contracts/"
          ]
        }
      },
      "imports": [
        "../../utils/introspection/IERC165Upgradeable.sol"
      ],
      "versionPragmas": [
        "^0.8.0"
      ],
      "artifacts": [
        "IERC1155Upgradeable"
      ]
    },
    "/Users/marcuspang/Desktop/Personal/radar-contracts/lib/openzeppelin-contracts-upgradeable/contracts/token/ERC1155/IERC1155ReceiverUpgradeable.sol": {
      "lastModificationDate": 1691019102259,
      "contentHash": "eb51ed084f6f7fd2c7098715c5690285",
      "sourceName": "lib/openzeppelin-contracts-upgradeable/contracts/token/ERC1155/IERC1155ReceiverUpgradeable.sol",
      "solcConfig": {
        "version": "0.8.19",
        "settings": {
          "optimizer": {
            "enabled": true,
            "runs": 200
          },
          "outputSelection": {
            "*": {
              "*": [
                "abi",
                "evm.bytecode",
                "evm.deployedBytecode",
                "evm.methodIdentifiers",
                "metadata",
                "storageLayout"
              ],
              "": [
                "ast"
              ]
            }
          },
          "remappings": [
            "ds-test/=lib/forge-std/lib/ds-test/src/",
            "erc4626-tests/=lib/openzeppelin-contracts/lib/erc4626-tests/",
            "forge-std/=lib/forge-std/src/",
            "@openzeppelin/contracts-upgradeable/=lib/openzeppelin-contracts-upgradeable/contracts/",
            "@openzeppelin/contracts/=lib/openzeppelin-contracts/contracts/",
            "ERC721A-Upgradeable/=lib/ERC721A-Upgradeable/contracts/",
            "openzeppelin-contracts-upgradeable/=lib/openzeppelin-contracts-upgradeable/",
            "openzeppelin-contracts/=lib/openzeppelin-contracts/",
            "openzeppelin/=lib/openzeppelin-contracts-upgradeable/contracts/"
          ]
        }
      },
      "imports": [
        "../../utils/introspection/IERC165Upgradeable.sol"
      ],
      "versionPragmas": [
        "^0.8.0"
      ],
      "artifacts": [
        "IERC1155ReceiverUpgradeable"
      ]
    },
    "/Users/marcuspang/Desktop/Personal/radar-contracts/lib/openzeppelin-contracts-upgradeable/contracts/token/ERC1155/extensions/IERC1155MetadataURIUpgradeable.sol": {
      "lastModificationDate": 1691019102260,
      "contentHash": "8b7e95c747e2dab3b5444b37410a8315",
      "sourceName": "lib/openzeppelin-contracts-upgradeable/contracts/token/ERC1155/extensions/IERC1155MetadataURIUpgradeable.sol",
      "solcConfig": {
        "version": "0.8.19",
        "settings": {
          "optimizer": {
            "enabled": true,
            "runs": 200
          },
          "outputSelection": {
            "*": {
              "*": [
                "abi",
                "evm.bytecode",
                "evm.deployedBytecode",
                "evm.methodIdentifiers",
                "metadata",
                "storageLayout"
              ],
              "": [
                "ast"
              ]
            }
          },
          "remappings": [
            "ds-test/=lib/forge-std/lib/ds-test/src/",
            "erc4626-tests/=lib/openzeppelin-contracts/lib/erc4626-tests/",
            "forge-std/=lib/forge-std/src/",
            "@openzeppelin/contracts-upgradeable/=lib/openzeppelin-contracts-upgradeable/contracts/",
            "@openzeppelin/contracts/=lib/openzeppelin-contracts/contracts/",
            "ERC721A-Upgradeable/=lib/ERC721A-Upgradeable/contracts/",
            "openzeppelin-contracts-upgradeable/=lib/openzeppelin-contracts-upgradeable/",
            "openzeppelin-contracts/=lib/openzeppelin-contracts/",
            "openzeppelin/=lib/openzeppelin-contracts-upgradeable/contracts/"
          ]
        }
      },
      "imports": [
        "../IERC1155Upgradeable.sol"
      ],
      "versionPragmas": [
        "^0.8.0"
      ],
      "artifacts": [
        "IERC1155MetadataURIUpgradeable"
      ]
    },
    "/Users/marcuspang/Desktop/Personal/radar-contracts/lib/openzeppelin-contracts-upgradeable/contracts/interfaces/draft-IERC1822Upgradeable.sol": {
      "lastModificationDate": 1691019102233,
      "contentHash": "a6883cfd85607b16c121a02728369eb3",
      "sourceName": "lib/openzeppelin-contracts-upgradeable/contracts/interfaces/draft-IERC1822Upgradeable.sol",
      "solcConfig": {
        "version": "0.8.19",
        "settings": {
          "optimizer": {
            "enabled": true,
            "runs": 200
          },
          "outputSelection": {
            "*": {
              "*": [
                "abi",
                "evm.bytecode",
                "evm.deployedBytecode",
                "evm.methodIdentifiers",
                "metadata",
                "storageLayout"
              ],
              "": [
                "ast"
              ]
            }
          },
          "remappings": [
            "ds-test/=lib/forge-std/lib/ds-test/src/",
            "erc4626-tests/=lib/openzeppelin-contracts/lib/erc4626-tests/",
            "forge-std/=lib/forge-std/src/",
            "@openzeppelin/contracts-upgradeable/=lib/openzeppelin-contracts-upgradeable/contracts/",
            "@openzeppelin/contracts/=lib/openzeppelin-contracts/contracts/",
            "ERC721A-Upgradeable/=lib/ERC721A-Upgradeable/contracts/",
            "openzeppelin-contracts-upgradeable/=lib/openzeppelin-contracts-upgradeable/",
            "openzeppelin-contracts/=lib/openzeppelin-contracts/",
            "openzeppelin/=lib/openzeppelin-contracts-upgradeable/contracts/"
          ]
        }
      },
      "imports": [],
      "versionPragmas": [
        "^0.8.0"
      ],
      "artifacts": [
        "IERC1822ProxiableUpgradeable"
      ]
    },
    "/Users/marcuspang/Desktop/Personal/radar-contracts/lib/openzeppelin-contracts-upgradeable/contracts/proxy/ERC1967/ERC1967UpgradeUpgradeable.sol": {
      "lastModificationDate": 1691019102256,
      "contentHash": "2587366284baa690cce0accaca1a20f9",
      "sourceName": "lib/openzeppelin-contracts-upgradeable/contracts/proxy/ERC1967/ERC1967UpgradeUpgradeable.sol",
      "solcConfig": {
        "version": "0.8.19",
        "settings": {
          "optimizer": {
            "enabled": true,
            "runs": 200
          },
          "outputSelection": {
            "*": {
              "*": [
                "abi",
                "evm.bytecode",
                "evm.deployedBytecode",
                "evm.methodIdentifiers",
                "metadata",
                "storageLayout"
              ],
              "": [
                "ast"
              ]
            }
          },
          "remappings": [
            "ds-test/=lib/forge-std/lib/ds-test/src/",
            "erc4626-tests/=lib/openzeppelin-contracts/lib/erc4626-tests/",
            "forge-std/=lib/forge-std/src/",
            "@openzeppelin/contracts-upgradeable/=lib/openzeppelin-contracts-upgradeable/contracts/",
            "@openzeppelin/contracts/=lib/openzeppelin-contracts/contracts/",
            "ERC721A-Upgradeable/=lib/ERC721A-Upgradeable/contracts/",
            "openzeppelin-contracts-upgradeable/=lib/openzeppelin-contracts-upgradeable/",
            "openzeppelin-contracts/=lib/openzeppelin-contracts/",
            "openzeppelin/=lib/openzeppelin-contracts-upgradeable/contracts/"
          ]
        }
      },
      "imports": [
        "../beacon/IBeaconUpgradeable.sol",
        "../../interfaces/IERC1967Upgradeable.sol",
        "../../interfaces/draft-IERC1822Upgradeable.sol",
        "../../utils/AddressUpgradeable.sol",
        "../../utils/StorageSlotUpgradeable.sol",
        "../utils/Initializable.sol"
      ],
      "versionPragmas": [
        "^0.8.2"
      ],
      "artifacts": [
        "ERC1967UpgradeUpgradeable"
      ]
    },
    "/Users/marcuspang/Desktop/Personal/radar-contracts/lib/openzeppelin-contracts-upgradeable/contracts/utils/StorageSlotUpgradeable.sol": {
      "lastModificationDate": 1691019102273,
      "contentHash": "02cf959b00ba5c650708472f195f8b29",
      "sourceName": "lib/openzeppelin-contracts-upgradeable/contracts/utils/StorageSlotUpgradeable.sol",
      "solcConfig": {
        "version": "0.8.19",
        "settings": {
          "optimizer": {
            "enabled": true,
            "runs": 200
          },
          "outputSelection": {
            "*": {
              "*": [
                "abi",
                "evm.bytecode",
                "evm.deployedBytecode",
                "evm.methodIdentifiers",
                "metadata",
                "storageLayout"
              ],
              "": [
                "ast"
              ]
            }
          },
          "remappings": [
            "ds-test/=lib/forge-std/lib/ds-test/src/",
            "erc4626-tests/=lib/openzeppelin-contracts/lib/erc4626-tests/",
            "forge-std/=lib/forge-std/src/",
            "@openzeppelin/contracts-upgradeable/=lib/openzeppelin-contracts-upgradeable/contracts/",
            "@openzeppelin/contracts/=lib/openzeppelin-contracts/contracts/",
            "ERC721A-Upgradeable/=lib/ERC721A-Upgradeable/contracts/",
            "openzeppelin-contracts-upgradeable/=lib/openzeppelin-contracts-upgradeable/",
            "openzeppelin-contracts/=lib/openzeppelin-contracts/",
            "openzeppelin/=lib/openzeppelin-contracts-upgradeable/contracts/"
          ]
        }
      },
      "imports": [],
      "versionPragmas": [
        "^0.8.0"
      ],
      "artifacts": [
        "StorageSlotUpgradeable"
      ]
    },
    "/Users/marcuspang/Desktop/Personal/radar-contracts/lib/openzeppelin-contracts-upgradeable/contracts/proxy/beacon/IBeaconUpgradeable.sol": {
      "lastModificationDate": 1691019102257,
      "contentHash": "21bffd733b4ca013e125a0ffe2e52254",
      "sourceName": "lib/openzeppelin-contracts-upgradeable/contracts/proxy/beacon/IBeaconUpgradeable.sol",
      "solcConfig": {
        "version": "0.8.19",
        "settings": {
          "optimizer": {
            "enabled": true,
            "runs": 200
          },
          "outputSelection": {
            "*": {
              "*": [
                "abi",
                "evm.bytecode",
                "evm.deployedBytecode",
                "evm.methodIdentifiers",
                "metadata",
                "storageLayout"
              ],
              "": [
                "ast"
              ]
            }
          },
          "remappings": [
            "ds-test/=lib/forge-std/lib/ds-test/src/",
            "erc4626-tests/=lib/openzeppelin-contracts/lib/erc4626-tests/",
            "forge-std/=lib/forge-std/src/",
            "@openzeppelin/contracts-upgradeable/=lib/openzeppelin-contracts-upgradeable/contracts/",
            "@openzeppelin/contracts/=lib/openzeppelin-contracts/contracts/",
            "ERC721A-Upgradeable/=lib/ERC721A-Upgradeable/contracts/",
            "openzeppelin-contracts-upgradeable/=lib/openzeppelin-contracts-upgradeable/",
            "openzeppelin-contracts/=lib/openzeppelin-contracts/",
            "openzeppelin/=lib/openzeppelin-contracts-upgradeable/contracts/"
          ]
        }
      },
      "imports": [],
      "versionPragmas": [
        "^0.8.0"
      ],
      "artifacts": [
        "IBeaconUpgradeable"
      ]
    },
    "/Users/marcuspang/Desktop/Personal/radar-contracts/lib/openzeppelin-contracts-upgradeable/contracts/interfaces/IERC1967Upgradeable.sol": {
      "lastModificationDate": 1691019102230,
      "contentHash": "a5421a5e611067b9202e83329fbf6fc7",
      "sourceName": "lib/openzeppelin-contracts-upgradeable/contracts/interfaces/IERC1967Upgradeable.sol",
      "solcConfig": {
        "version": "0.8.19",
        "settings": {
          "optimizer": {
            "enabled": true,
            "runs": 200
          },
          "outputSelection": {
            "*": {
              "*": [
                "abi",
                "evm.bytecode",
                "evm.deployedBytecode",
                "evm.methodIdentifiers",
                "metadata",
                "storageLayout"
              ],
              "": [
                "ast"
              ]
            }
          },
          "remappings": [
            "ds-test/=lib/forge-std/lib/ds-test/src/",
            "erc4626-tests/=lib/openzeppelin-contracts/lib/erc4626-tests/",
            "forge-std/=lib/forge-std/src/",
            "@openzeppelin/contracts-upgradeable/=lib/openzeppelin-contracts-upgradeable/contracts/",
            "@openzeppelin/contracts/=lib/openzeppelin-contracts/contracts/",
            "ERC721A-Upgradeable/=lib/ERC721A-Upgradeable/contracts/",
            "openzeppelin-contracts-upgradeable/=lib/openzeppelin-contracts-upgradeable/",
            "openzeppelin-contracts/=lib/openzeppelin-contracts/",
            "openzeppelin/=lib/openzeppelin-contracts-upgradeable/contracts/"
          ]
        }
      },
      "imports": [],
      "versionPragmas": [
        "^0.8.0"
      ],
      "artifacts": [
        "IERC1967Upgradeable"
      ]
    },
    "/Users/marcuspang/Desktop/Personal/radar-contracts/lib/openzeppelin-contracts-upgradeable/contracts/token/ERC721/ERC721Upgradeable.sol": {
      "lastModificationDate": 1691019102266,
      "contentHash": "523926739c7d64c61fd57080f4bbcb05",
      "sourceName": "lib/openzeppelin-contracts-upgradeable/contracts/token/ERC721/ERC721Upgradeable.sol",
      "solcConfig": {
        "version": "0.8.19",
        "settings": {
          "optimizer": {
            "enabled": true,
            "runs": 200
          },
          "outputSelection": {
            "*": {
              "*": [
                "abi",
                "evm.bytecode",
                "evm.deployedBytecode",
                "evm.methodIdentifiers",
                "metadata",
                "storageLayout"
              ],
              "": [
                "ast"
              ]
            }
          },
          "remappings": [
            "ds-test/=lib/forge-std/lib/ds-test/src/",
            "erc4626-tests/=lib/openzeppelin-contracts/lib/erc4626-tests/",
            "forge-std/=lib/forge-std/src/",
            "@openzeppelin/contracts-upgradeable/=lib/openzeppelin-contracts-upgradeable/contracts/",
            "@openzeppelin/contracts/=lib/openzeppelin-contracts/contracts/",
            "ERC721A-Upgradeable/=lib/ERC721A-Upgradeable/contracts/",
            "openzeppelin-contracts-upgradeable/=lib/openzeppelin-contracts-upgradeable/",
            "openzeppelin-contracts/=lib/openzeppelin-contracts/",
            "openzeppelin/=lib/openzeppelin-contracts-upgradeable/contracts/"
          ]
        }
      },
      "imports": [
        "./IERC721Upgradeable.sol",
        "./IERC721ReceiverUpgradeable.sol",
        "./extensions/IERC721MetadataUpgradeable.sol",
        "../../utils/AddressUpgradeable.sol",
        "../../utils/ContextUpgradeable.sol",
        "../../utils/StringsUpgradeable.sol",
        "../../utils/introspection/ERC165Upgradeable.sol",
        "../../proxy/utils/Initializable.sol"
      ],
      "versionPragmas": [
        "^0.8.0"
      ],
      "artifacts": [
        "ERC721Upgradeable"
      ]
    },
    "/Users/marcuspang/Desktop/Personal/radar-contracts/lib/openzeppelin-contracts-upgradeable/contracts/token/ERC721/IERC721ReceiverUpgradeable.sol": {
      "lastModificationDate": 1691019102266,
      "contentHash": "ba28cf60b52b00d2b3a190bcdf0952bd",
      "sourceName": "lib/openzeppelin-contracts-upgradeable/contracts/token/ERC721/IERC721ReceiverUpgradeable.sol",
      "solcConfig": {
        "version": "0.8.19",
        "settings": {
          "optimizer": {
            "enabled": true,
            "runs": 200
          },
          "outputSelection": {
            "*": {
              "*": [
                "abi",
                "evm.bytecode",
                "evm.deployedBytecode",
                "evm.methodIdentifiers",
                "metadata",
                "storageLayout"
              ],
              "": [
                "ast"
              ]
            }
          },
          "remappings": [
            "ds-test/=lib/forge-std/lib/ds-test/src/",
            "erc4626-tests/=lib/openzeppelin-contracts/lib/erc4626-tests/",
            "forge-std/=lib/forge-std/src/",
            "@openzeppelin/contracts-upgradeable/=lib/openzeppelin-contracts-upgradeable/contracts/",
            "@openzeppelin/contracts/=lib/openzeppelin-contracts/contracts/",
            "ERC721A-Upgradeable/=lib/ERC721A-Upgradeable/contracts/",
            "openzeppelin-contracts-upgradeable/=lib/openzeppelin-contracts-upgradeable/",
            "openzeppelin-contracts/=lib/openzeppelin-contracts/",
            "openzeppelin/=lib/openzeppelin-contracts-upgradeable/contracts/"
          ]
        }
      },
      "imports": [],
      "versionPragmas": [
        "^0.8.0"
      ],
      "artifacts": [
        "IERC721ReceiverUpgradeable"
      ]
    },
    "/Users/marcuspang/Desktop/Personal/radar-contracts/lib/openzeppelin-contracts-upgradeable/contracts/token/ERC721/IERC721Upgradeable.sol": {
      "lastModificationDate": 1691019102266,
      "contentHash": "f6c6e71ba8413a4ba32871610dba0658",
      "sourceName": "lib/openzeppelin-contracts-upgradeable/contracts/token/ERC721/IERC721Upgradeable.sol",
      "solcConfig": {
        "version": "0.8.19",
        "settings": {
          "optimizer": {
            "enabled": true,
            "runs": 200
          },
          "outputSelection": {
            "*": {
              "*": [
                "abi",
                "evm.bytecode",
                "evm.deployedBytecode",
                "evm.methodIdentifiers",
                "metadata",
                "storageLayout"
              ],
              "": [
                "ast"
              ]
            }
          },
          "remappings": [
            "ds-test/=lib/forge-std/lib/ds-test/src/",
            "erc4626-tests/=lib/openzeppelin-contracts/lib/erc4626-tests/",
            "forge-std/=lib/forge-std/src/",
            "@openzeppelin/contracts-upgradeable/=lib/openzeppelin-contracts-upgradeable/contracts/",
            "@openzeppelin/contracts/=lib/openzeppelin-contracts/contracts/",
            "ERC721A-Upgradeable/=lib/ERC721A-Upgradeable/contracts/",
            "openzeppelin-contracts-upgradeable/=lib/openzeppelin-contracts-upgradeable/",
            "openzeppelin-contracts/=lib/openzeppelin-contracts/",
            "openzeppelin/=lib/openzeppelin-contracts-upgradeable/contracts/"
          ]
        }
      },
      "imports": [
        "../../utils/introspection/IERC165Upgradeable.sol"
      ],
      "versionPragmas": [
        "^0.8.0"
      ],
      "artifacts": [
        "IERC721Upgradeable"
      ]
    },
    "/Users/marcuspang/Desktop/Personal/radar-contracts/lib/openzeppelin-contracts-upgradeable/contracts/token/ERC721/extensions/IERC721MetadataUpgradeable.sol": {
      "lastModificationDate": 1691019102268,
      "contentHash": "76212ca0265501d1eb3dd1175e6afca4",
      "sourceName": "lib/openzeppelin-contracts-upgradeable/contracts/token/ERC721/extensions/IERC721MetadataUpgradeable.sol",
      "solcConfig": {
        "version": "0.8.19",
        "settings": {
          "optimizer": {
            "enabled": true,
            "runs": 200
          },
          "outputSelection": {
            "*": {
              "*": [
                "abi",
                "evm.bytecode",
                "evm.deployedBytecode",
                "evm.methodIdentifiers",
                "metadata",
                "storageLayout"
              ],
              "": [
                "ast"
              ]
            }
          },
          "remappings": [
            "ds-test/=lib/forge-std/lib/ds-test/src/",
            "erc4626-tests/=lib/openzeppelin-contracts/lib/erc4626-tests/",
            "forge-std/=lib/forge-std/src/",
            "@openzeppelin/contracts-upgradeable/=lib/openzeppelin-contracts-upgradeable/contracts/",
            "@openzeppelin/contracts/=lib/openzeppelin-contracts/contracts/",
            "ERC721A-Upgradeable/=lib/ERC721A-Upgradeable/contracts/",
            "openzeppelin-contracts-upgradeable/=lib/openzeppelin-contracts-upgradeable/",
            "openzeppelin-contracts/=lib/openzeppelin-contracts/",
            "openzeppelin/=lib/openzeppelin-contracts-upgradeable/contracts/"
          ]
        }
      },
      "imports": [
        "../IERC721Upgradeable.sol"
      ],
      "versionPragmas": [
        "^0.8.0"
      ],
      "artifacts": [
        "IERC721MetadataUpgradeable"
      ]
    },
    "/Users/marcuspang/Desktop/Personal/radar-contracts/lib/openzeppelin-contracts-upgradeable/contracts/token/ERC721/extensions/ERC721URIStorageUpgradeable.sol": {
      "lastModificationDate": 1691019102268,
      "contentHash": "47e0570153178b284d04fdc8947af91b",
      "sourceName": "lib/openzeppelin-contracts-upgradeable/contracts/token/ERC721/extensions/ERC721URIStorageUpgradeable.sol",
      "solcConfig": {
        "version": "0.8.19",
        "settings": {
          "optimizer": {
            "enabled": true,
            "runs": 200
          },
          "outputSelection": {
            "*": {
              "*": [
                "abi",
                "evm.bytecode",
                "evm.deployedBytecode",
                "evm.methodIdentifiers",
                "metadata",
                "storageLayout"
              ],
              "": [
                "ast"
              ]
            }
          },
          "remappings": [
            "ds-test/=lib/forge-std/lib/ds-test/src/",
            "erc4626-tests/=lib/openzeppelin-contracts/lib/erc4626-tests/",
            "forge-std/=lib/forge-std/src/",
            "@openzeppelin/contracts-upgradeable/=lib/openzeppelin-contracts-upgradeable/contracts/",
            "@openzeppelin/contracts/=lib/openzeppelin-contracts/contracts/",
            "ERC721A-Upgradeable/=lib/ERC721A-Upgradeable/contracts/",
            "openzeppelin-contracts-upgradeable/=lib/openzeppelin-contracts-upgradeable/",
            "openzeppelin-contracts/=lib/openzeppelin-contracts/",
            "openzeppelin/=lib/openzeppelin-contracts-upgradeable/contracts/"
          ]
        }
      },
      "imports": [
        "../ERC721Upgradeable.sol",
        "../../../interfaces/IERC4906Upgradeable.sol",
        "../../../proxy/utils/Initializable.sol"
      ],
      "versionPragmas": [
        "^0.8.0"
      ],
      "artifacts": [
        "ERC721URIStorageUpgradeable"
      ]
    },
    "/Users/marcuspang/Desktop/Personal/radar-contracts/lib/openzeppelin-contracts-upgradeable/contracts/interfaces/IERC4906Upgradeable.sol": {
      "lastModificationDate": 1691019102231,
      "contentHash": "fe5233feb20121d3fcadf24db464f5f8",
      "sourceName": "lib/openzeppelin-contracts-upgradeable/contracts/interfaces/IERC4906Upgradeable.sol",
      "solcConfig": {
        "version": "0.8.19",
        "settings": {
          "optimizer": {
            "enabled": true,
            "runs": 200
          },
          "outputSelection": {
            "*": {
              "*": [
                "abi",
                "evm.bytecode",
                "evm.deployedBytecode",
                "evm.methodIdentifiers",
                "metadata",
                "storageLayout"
              ],
              "": [
                "ast"
              ]
            }
          },
          "remappings": [
            "ds-test/=lib/forge-std/lib/ds-test/src/",
            "erc4626-tests/=lib/openzeppelin-contracts/lib/erc4626-tests/",
            "forge-std/=lib/forge-std/src/",
            "@openzeppelin/contracts-upgradeable/=lib/openzeppelin-contracts-upgradeable/contracts/",
            "@openzeppelin/contracts/=lib/openzeppelin-contracts/contracts/",
            "ERC721A-Upgradeable/=lib/ERC721A-Upgradeable/contracts/",
            "openzeppelin-contracts-upgradeable/=lib/openzeppelin-contracts-upgradeable/",
            "openzeppelin-contracts/=lib/openzeppelin-contracts/",
            "openzeppelin/=lib/openzeppelin-contracts-upgradeable/contracts/"
          ]
        }
      },
      "imports": [
        "./IERC165Upgradeable.sol",
        "./IERC721Upgradeable.sol"
      ],
      "versionPragmas": [
        "^0.8.0"
      ],
      "artifacts": [
        "IERC4906Upgradeable"
      ]
    },
    "/Users/marcuspang/Desktop/Personal/radar-contracts/lib/openzeppelin-contracts-upgradeable/contracts/interfaces/IERC165Upgradeable.sol": {
      "lastModificationDate": 1691019102229,
      "contentHash": "0ce0dc23b57eb688403ad5169cc18a7d",
      "sourceName": "lib/openzeppelin-contracts-upgradeable/contracts/interfaces/IERC165Upgradeable.sol",
      "solcConfig": {
        "version": "0.8.19",
        "settings": {
          "optimizer": {
            "enabled": true,
            "runs": 200
          },
          "outputSelection": {
            "*": {
              "*": [
                "abi",
                "evm.bytecode",
                "evm.deployedBytecode",
                "evm.methodIdentifiers",
                "metadata",
                "storageLayout"
              ],
              "": [
                "ast"
              ]
            }
          },
          "remappings": [
            "ds-test/=lib/forge-std/lib/ds-test/src/",
            "erc4626-tests/=lib/openzeppelin-contracts/lib/erc4626-tests/",
            "forge-std/=lib/forge-std/src/",
            "@openzeppelin/contracts-upgradeable/=lib/openzeppelin-contracts-upgradeable/contracts/",
            "@openzeppelin/contracts/=lib/openzeppelin-contracts/contracts/",
            "ERC721A-Upgradeable/=lib/ERC721A-Upgradeable/contracts/",
            "openzeppelin-contracts-upgradeable/=lib/openzeppelin-contracts-upgradeable/",
            "openzeppelin-contracts/=lib/openzeppelin-contracts/",
            "openzeppelin/=lib/openzeppelin-contracts-upgradeable/contracts/"
          ]
        }
      },
      "imports": [
        "../utils/introspection/IERC165Upgradeable.sol"
      ],
      "versionPragmas": [
        "^0.8.0"
      ],
      "artifacts": []
    },
    "/Users/marcuspang/Desktop/Personal/radar-contracts/lib/openzeppelin-contracts-upgradeable/contracts/interfaces/IERC721Upgradeable.sol": {
      "lastModificationDate": 1691019102232,
      "contentHash": "b6d2f759a0c41967c68a26c21d5ecbe4",
      "sourceName": "lib/openzeppelin-contracts-upgradeable/contracts/interfaces/IERC721Upgradeable.sol",
      "solcConfig": {
        "version": "0.8.19",
        "settings": {
          "optimizer": {
            "enabled": true,
            "runs": 200
          },
          "outputSelection": {
            "*": {
              "*": [
                "abi",
                "evm.bytecode",
                "evm.deployedBytecode",
                "evm.methodIdentifiers",
                "metadata",
                "storageLayout"
              ],
              "": [
                "ast"
              ]
            }
          },
          "remappings": [
            "ds-test/=lib/forge-std/lib/ds-test/src/",
            "erc4626-tests/=lib/openzeppelin-contracts/lib/erc4626-tests/",
            "forge-std/=lib/forge-std/src/",
            "@openzeppelin/contracts-upgradeable/=lib/openzeppelin-contracts-upgradeable/contracts/",
            "@openzeppelin/contracts/=lib/openzeppelin-contracts/contracts/",
            "ERC721A-Upgradeable/=lib/ERC721A-Upgradeable/contracts/",
            "openzeppelin-contracts-upgradeable/=lib/openzeppelin-contracts-upgradeable/",
            "openzeppelin-contracts/=lib/openzeppelin-contracts/",
            "openzeppelin/=lib/openzeppelin-contracts-upgradeable/contracts/"
          ]
        }
      },
      "imports": [
        "../token/ERC721/IERC721Upgradeable.sol"
      ],
      "versionPragmas": [
        "^0.8.0"
      ],
      "artifacts": []
    },
    "/Users/marcuspang/Desktop/Personal/radar-contracts/lib/openzeppelin-contracts-upgradeable/contracts/access/OwnableUpgradeable.sol": {
      "lastModificationDate": 1691019102220,
      "contentHash": "db24b956904575cc79d02867ec03263c",
      "sourceName": "lib/openzeppelin-contracts-upgradeable/contracts/access/OwnableUpgradeable.sol",
      "solcConfig": {
        "version": "0.8.19",
        "settings": {
          "optimizer": {
            "enabled": true,
            "runs": 200
          },
          "outputSelection": {
            "*": {
              "*": [
                "abi",
                "evm.bytecode",
                "evm.deployedBytecode",
                "evm.methodIdentifiers",
                "metadata",
                "storageLayout"
              ],
              "": [
                "ast"
              ]
            }
          },
          "remappings": [
            "ds-test/=lib/forge-std/lib/ds-test/src/",
            "erc4626-tests/=lib/openzeppelin-contracts/lib/erc4626-tests/",
            "forge-std/=lib/forge-std/src/",
            "@openzeppelin/contracts-upgradeable/=lib/openzeppelin-contracts-upgradeable/contracts/",
            "@openzeppelin/contracts/=lib/openzeppelin-contracts/contracts/",
            "ERC721A-Upgradeable/=lib/ERC721A-Upgradeable/contracts/",
            "openzeppelin-contracts-upgradeable/=lib/openzeppelin-contracts-upgradeable/",
            "openzeppelin-contracts/=lib/openzeppelin-contracts/",
            "openzeppelin/=lib/openzeppelin-contracts-upgradeable/contracts/"
          ]
        }
      },
      "imports": [
        "../utils/ContextUpgradeable.sol",
        "../proxy/utils/Initializable.sol"
      ],
      "versionPragmas": [
        "^0.8.0"
      ],
      "artifacts": [
        "OwnableUpgradeable"
      ]
    },
    "/Users/marcuspang/Desktop/Personal/radar-contracts/src/RadarVideoNFT.sol": {
      "lastModificationDate": 1697133969017,
      "contentHash": "c9f9e866c5a055a6bf61fc15322b2965",
      "sourceName": "src/RadarVideoNFT.sol",
      "solcConfig": {
        "version": "0.8.19",
        "settings": {
          "optimizer": {
            "enabled": true,
            "runs": 200
          },
          "outputSelection": {
            "*": {
              "*": [
                "abi",
                "evm.bytecode",
                "evm.deployedBytecode",
                "evm.methodIdentifiers",
                "metadata",
                "storageLayout"
              ],
              "": [
                "ast"
              ]
            }
          },
          "remappings": [
            "ds-test/=lib/forge-std/lib/ds-test/src/",
            "erc4626-tests/=lib/openzeppelin-contracts/lib/erc4626-tests/",
            "forge-std/=lib/forge-std/src/",
            "@openzeppelin/contracts-upgradeable/=lib/openzeppelin-contracts-upgradeable/contracts/",
            "@openzeppelin/contracts/=lib/openzeppelin-contracts/contracts/",
            "ERC721A-Upgradeable/=lib/ERC721A-Upgradeable/contracts/",
            "openzeppelin-contracts-upgradeable/=lib/openzeppelin-contracts-upgradeable/",
            "openzeppelin-contracts/=lib/openzeppelin-contracts/",
            "openzeppelin/=lib/openzeppelin-contracts-upgradeable/contracts/"
          ]
        }
      },
      "imports": [
        "@openzeppelin/contracts-upgradeable/token/ERC721/ERC721Upgradeable.sol",
        "@openzeppelin/contracts-upgradeable/token/ERC721/extensions/ERC721URIStorageUpgradeable.sol",
        "@openzeppelin/contracts-upgradeable/access/OwnableUpgradeable.sol",
        "@openzeppelin/contracts-upgradeable/proxy/utils/Initializable.sol",
        "@openzeppelin/contracts-upgradeable/proxy/utils/UUPSUpgradeable.sol"
      ],
      "versionPragmas": [
        "^0.8.13"
      ],
      "artifacts": [
        "RadarVideoNFT"
      ]
    },
    "/Users/marcuspang/Desktop/Personal/radar-contracts/lib/openzeppelin-contracts/contracts/proxy/Proxy.sol": {
      "lastModificationDate": 1691019093908,
      "contentHash": "40b3d81a836d50ff47e03893dcaaf204",
      "sourceName": "lib/openzeppelin-contracts/contracts/proxy/Proxy.sol",
      "solcConfig": {
        "version": "0.8.19",
        "settings": {
          "optimizer": {
            "enabled": true,
            "runs": 200
          },
          "outputSelection": {
            "*": {
              "*": [
                "abi",
                "evm.bytecode",
                "evm.deployedBytecode",
                "evm.methodIdentifiers",
                "metadata",
                "storageLayout"
              ],
              "": [
                "ast"
              ]
            }
          },
          "remappings": [
            "ds-test/=lib/forge-std/lib/ds-test/src/",
            "erc4626-tests/=lib/openzeppelin-contracts/lib/erc4626-tests/",
            "forge-std/=lib/forge-std/src/",
            "@openzeppelin/contracts-upgradeable/=lib/openzeppelin-contracts-upgradeable/contracts/",
            "@openzeppelin/contracts/=lib/openzeppelin-contracts/contracts/",
            "ERC721A-Upgradeable/=lib/ERC721A-Upgradeable/contracts/",
            "openzeppelin-contracts-upgradeable/=lib/openzeppelin-contracts-upgradeable/",
            "openzeppelin-contracts/=lib/openzeppelin-contracts/",
            "openzeppelin/=lib/openzeppelin-contracts-upgradeable/contracts/"
          ]
        }
      },
      "imports": [],
      "versionPragmas": [
        "^0.8.0"
      ],
      "artifacts": [
        "Proxy"
      ]
    },
    "/Users/marcuspang/Desktop/Personal/radar-contracts/lib/openzeppelin-contracts/contracts/proxy/ERC1967/ERC1967Upgrade.sol": {
      "lastModificationDate": 1691019093908,
      "contentHash": "a127706394bead18392601a20d44867a",
      "sourceName": "lib/openzeppelin-contracts/contracts/proxy/ERC1967/ERC1967Upgrade.sol",
      "solcConfig": {
        "version": "0.8.19",
        "settings": {
          "optimizer": {
            "enabled": true,
            "runs": 200
          },
          "outputSelection": {
            "*": {
              "*": [
                "abi",
                "evm.bytecode",
                "evm.deployedBytecode",
                "evm.methodIdentifiers",
                "metadata",
                "storageLayout"
              ],
              "": [
                "ast"
              ]
            }
          },
          "remappings": [
            "ds-test/=lib/forge-std/lib/ds-test/src/",
            "erc4626-tests/=lib/openzeppelin-contracts/lib/erc4626-tests/",
            "forge-std/=lib/forge-std/src/",
            "@openzeppelin/contracts-upgradeable/=lib/openzeppelin-contracts-upgradeable/contracts/",
            "@openzeppelin/contracts/=lib/openzeppelin-contracts/contracts/",
            "ERC721A-Upgradeable/=lib/ERC721A-Upgradeable/contracts/",
            "openzeppelin-contracts-upgradeable/=lib/openzeppelin-contracts-upgradeable/",
            "openzeppelin-contracts/=lib/openzeppelin-contracts/",
            "openzeppelin/=lib/openzeppelin-contracts-upgradeable/contracts/"
          ]
        }
      },
      "imports": [
        "../beacon/IBeacon.sol",
        "../../interfaces/IERC1967.sol",
        "../../interfaces/draft-IERC1822.sol",
        "../../utils/Address.sol",
        "../../utils/StorageSlot.sol"
      ],
      "versionPragmas": [
        "^0.8.2"
      ],
      "artifacts": [
        "ERC1967Upgrade"
      ]
    },
    "/Users/marcuspang/Desktop/Personal/radar-contracts/lib/openzeppelin-contracts/contracts/interfaces/draft-IERC1822.sol": {
      "lastModificationDate": 1691019093886,
      "contentHash": "2858d98e74e67987ec81b39605230b74",
      "sourceName": "lib/openzeppelin-contracts/contracts/interfaces/draft-IERC1822.sol",
      "solcConfig": {
        "version": "0.8.19",
        "settings": {
          "optimizer": {
            "enabled": true,
            "runs": 200
          },
          "outputSelection": {
            "*": {
              "*": [
                "abi",
                "evm.bytecode",
                "evm.deployedBytecode",
                "evm.methodIdentifiers",
                "metadata",
                "storageLayout"
              ],
              "": [
                "ast"
              ]
            }
          },
          "remappings": [
            "ds-test/=lib/forge-std/lib/ds-test/src/",
            "erc4626-tests/=lib/openzeppelin-contracts/lib/erc4626-tests/",
            "forge-std/=lib/forge-std/src/",
            "@openzeppelin/contracts-upgradeable/=lib/openzeppelin-contracts-upgradeable/contracts/",
            "@openzeppelin/contracts/=lib/openzeppelin-contracts/contracts/",
            "ERC721A-Upgradeable/=lib/ERC721A-Upgradeable/contracts/",
            "openzeppelin-contracts-upgradeable/=lib/openzeppelin-contracts-upgradeable/",
            "openzeppelin-contracts/=lib/openzeppelin-contracts/",
            "openzeppelin/=lib/openzeppelin-contracts-upgradeable/contracts/"
          ]
        }
      },
      "imports": [],
      "versionPragmas": [
        "^0.8.0"
      ],
      "artifacts": [
        "IERC1822Proxiable"
      ]
    },
    "/Users/marcuspang/Desktop/Personal/radar-contracts/lib/openzeppelin-contracts/contracts/utils/Address.sol": {
      "lastModificationDate": 1691019093923,
      "contentHash": "211ffd288c1588ba8c10eae668ca3c66",
      "sourceName": "lib/openzeppelin-contracts/contracts/utils/Address.sol",
      "solcConfig": {
        "version": "0.8.19",
        "settings": {
          "optimizer": {
            "enabled": true,
            "runs": 200
          },
          "outputSelection": {
            "*": {
              "*": [
                "abi",
                "evm.bytecode",
                "evm.deployedBytecode",
                "evm.methodIdentifiers",
                "metadata",
                "storageLayout"
              ],
              "": [
                "ast"
              ]
            }
          },
          "remappings": [
            "ds-test/=lib/forge-std/lib/ds-test/src/",
            "erc4626-tests/=lib/openzeppelin-contracts/lib/erc4626-tests/",
            "forge-std/=lib/forge-std/src/",
            "@openzeppelin/contracts-upgradeable/=lib/openzeppelin-contracts-upgradeable/contracts/",
            "@openzeppelin/contracts/=lib/openzeppelin-contracts/contracts/",
            "ERC721A-Upgradeable/=lib/ERC721A-Upgradeable/contracts/",
            "openzeppelin-contracts-upgradeable/=lib/openzeppelin-contracts-upgradeable/",
            "openzeppelin-contracts/=lib/openzeppelin-contracts/",
            "openzeppelin/=lib/openzeppelin-contracts-upgradeable/contracts/"
          ]
        }
      },
      "imports": [],
      "versionPragmas": [
        "^0.8.1"
      ],
      "artifacts": [
        "Address"
      ]
    },
    "/Users/marcuspang/Desktop/Personal/radar-contracts/lib/openzeppelin-contracts/contracts/utils/StorageSlot.sol": {
      "lastModificationDate": 1691019093925,
      "contentHash": "682f7dd1f2e1147c8390e7575deceb2d",
      "sourceName": "lib/openzeppelin-contracts/contracts/utils/StorageSlot.sol",
      "solcConfig": {
        "version": "0.8.19",
        "settings": {
          "optimizer": {
            "enabled": true,
            "runs": 200
          },
          "outputSelection": {
            "*": {
              "*": [
                "abi",
                "evm.bytecode",
                "evm.deployedBytecode",
                "evm.methodIdentifiers",
                "metadata",
                "storageLayout"
              ],
              "": [
                "ast"
              ]
            }
          },
          "remappings": [
            "ds-test/=lib/forge-std/lib/ds-test/src/",
            "erc4626-tests/=lib/openzeppelin-contracts/lib/erc4626-tests/",
            "forge-std/=lib/forge-std/src/",
            "@openzeppelin/contracts-upgradeable/=lib/openzeppelin-contracts-upgradeable/contracts/",
            "@openzeppelin/contracts/=lib/openzeppelin-contracts/contracts/",
            "ERC721A-Upgradeable/=lib/ERC721A-Upgradeable/contracts/",
            "openzeppelin-contracts-upgradeable/=lib/openzeppelin-contracts-upgradeable/",
            "openzeppelin-contracts/=lib/openzeppelin-contracts/",
            "openzeppelin/=lib/openzeppelin-contracts-upgradeable/contracts/"
          ]
        }
      },
      "imports": [],
      "versionPragmas": [
        "^0.8.0"
      ],
      "artifacts": [
        "StorageSlot"
      ]
    },
    "/Users/marcuspang/Desktop/Personal/radar-contracts/lib/openzeppelin-contracts/contracts/interfaces/IERC1967.sol": {
      "lastModificationDate": 1691019093883,
      "contentHash": "d0d060231a45da7a1eecbb5cd286fa40",
      "sourceName": "lib/openzeppelin-contracts/contracts/interfaces/IERC1967.sol",
      "solcConfig": {
        "version": "0.8.19",
        "settings": {
          "optimizer": {
            "enabled": true,
            "runs": 200
          },
          "outputSelection": {
            "*": {
              "*": [
                "abi",
                "evm.bytecode",
                "evm.deployedBytecode",
                "evm.methodIdentifiers",
                "metadata",
                "storageLayout"
              ],
              "": [
                "ast"
              ]
            }
          },
          "remappings": [
            "ds-test/=lib/forge-std/lib/ds-test/src/",
            "erc4626-tests/=lib/openzeppelin-contracts/lib/erc4626-tests/",
            "forge-std/=lib/forge-std/src/",
            "@openzeppelin/contracts-upgradeable/=lib/openzeppelin-contracts-upgradeable/contracts/",
            "@openzeppelin/contracts/=lib/openzeppelin-contracts/contracts/",
            "ERC721A-Upgradeable/=lib/ERC721A-Upgradeable/contracts/",
            "openzeppelin-contracts-upgradeable/=lib/openzeppelin-contracts-upgradeable/",
            "openzeppelin-contracts/=lib/openzeppelin-contracts/",
            "openzeppelin/=lib/openzeppelin-contracts-upgradeable/contracts/"
          ]
        }
      },
      "imports": [],
      "versionPragmas": [
        "^0.8.0"
      ],
      "artifacts": [
        "IERC1967"
      ]
    },
    "/Users/marcuspang/Desktop/Personal/radar-contracts/lib/openzeppelin-contracts/contracts/proxy/beacon/IBeacon.sol": {
      "lastModificationDate": 1691019093908,
      "contentHash": "b6bd23bf19e90b771337037706470933",
      "sourceName": "lib/openzeppelin-contracts/contracts/proxy/beacon/IBeacon.sol",
      "solcConfig": {
        "version": "0.8.19",
        "settings": {
          "optimizer": {
            "enabled": true,
            "runs": 200
          },
          "outputSelection": {
            "*": {
              "*": [
                "abi",
                "evm.bytecode",
                "evm.deployedBytecode",
                "evm.methodIdentifiers",
                "metadata",
                "storageLayout"
              ],
              "": [
                "ast"
              ]
            }
          },
          "remappings": [
            "ds-test/=lib/forge-std/lib/ds-test/src/",
            "erc4626-tests/=lib/openzeppelin-contracts/lib/erc4626-tests/",
            "forge-std/=lib/forge-std/src/",
            "@openzeppelin/contracts-upgradeable/=lib/openzeppelin-contracts-upgradeable/contracts/",
            "@openzeppelin/contracts/=lib/openzeppelin-contracts/contracts/",
            "ERC721A-Upgradeable/=lib/ERC721A-Upgradeable/contracts/",
            "openzeppelin-contracts-upgradeable/=lib/openzeppelin-contracts-upgradeable/",
            "openzeppelin-contracts/=lib/openzeppelin-contracts/",
            "openzeppelin/=lib/openzeppelin-contracts-upgradeable/contracts/"
          ]
        }
      },
      "imports": [],
      "versionPragmas": [
        "^0.8.0"
      ],
      "artifacts": [
        "IBeacon"
      ]
    },
    "/Users/marcuspang/Desktop/Personal/radar-contracts/src/Editions/Editions.sol": {
      "lastModificationDate": 1697818426245,
      "contentHash": "c9b6d8b173e44f3c8f98b1e4b43c433a",
      "sourceName": "src/Editions/Editions.sol",
      "solcConfig": {
        "version": "0.8.19",
        "settings": {
          "optimizer": {
            "enabled": true,
            "runs": 200
          },
          "outputSelection": {
            "*": {
              "*": [
                "abi",
                "evm.bytecode",
                "evm.deployedBytecode",
                "evm.methodIdentifiers",
                "metadata",
                "storageLayout"
              ],
              "": [
                "ast"
              ]
            }
          },
          "remappings": [
            "ds-test/=lib/forge-std/lib/ds-test/src/",
            "erc4626-tests/=lib/openzeppelin-contracts/lib/erc4626-tests/",
            "forge-std/=lib/forge-std/src/",
            "@openzeppelin/contracts-upgradeable/=lib/openzeppelin-contracts-upgradeable/contracts/",
            "@openzeppelin/contracts/=lib/openzeppelin-contracts/contracts/",
            "ERC721A-Upgradeable/=lib/ERC721A-Upgradeable/contracts/",
            "openzeppelin-contracts-upgradeable/=lib/openzeppelin-contracts-upgradeable/",
            "openzeppelin-contracts/=lib/openzeppelin-contracts/",
            "openzeppelin/=lib/openzeppelin-contracts-upgradeable/contracts/"
          ]
        }
      },
      "imports": [
        "@openzeppelin/contracts-upgradeable/token/ERC1155/ERC1155Upgradeable.sol",
        "@openzeppelin/contracts-upgradeable/access/AccessControlUpgradeable.sol",
        "@openzeppelin/contracts-upgradeable/security/PausableUpgradeable.sol",
        "@openzeppelin/contracts-upgradeable/token/ERC1155/extensions/ERC1155BurnableUpgradeable.sol",
        "@openzeppelin/contracts-upgradeable/token/ERC1155/extensions/ERC1155SupplyUpgradeable.sol",
        "@openzeppelin/contracts-upgradeable/proxy/utils/Initializable.sol",
        "@openzeppelin/contracts-upgradeable/proxy/utils/UUPSUpgradeable.sol",
        "@openzeppelin/contracts/utils/structs/BitMaps.sol",
        "@openzeppelin/contracts/utils/Strings.sol",
        "./EditionsRoles.sol",
        "./IEditions.sol",
        "./EditionsStructs.sol"
      ],
      "versionPragmas": [
        "^0.8.13"
      ],
      "artifacts": [
        "Editions"
      ]
    },
    "/Users/marcuspang/Desktop/Personal/radar-contracts/src/Editions/IEditions.sol": {
      "lastModificationDate": 1697091123181,
      "contentHash": "aef3e3b2d24af05279d6ff315f237795",
      "sourceName": "src/Editions/IEditions.sol",
      "solcConfig": {
        "version": "0.8.19",
        "settings": {
          "optimizer": {
            "enabled": true,
            "runs": 200
          },
          "outputSelection": {
            "*": {
              "*": [
                "abi",
                "evm.bytecode",
                "evm.deployedBytecode",
                "evm.methodIdentifiers",
                "metadata",
                "storageLayout"
              ],
              "": [
                "ast"
              ]
            }
          },
          "remappings": [
            "ds-test/=lib/forge-std/lib/ds-test/src/",
            "erc4626-tests/=lib/openzeppelin-contracts/lib/erc4626-tests/",
            "forge-std/=lib/forge-std/src/",
            "@openzeppelin/contracts-upgradeable/=lib/openzeppelin-contracts-upgradeable/contracts/",
            "@openzeppelin/contracts/=lib/openzeppelin-contracts/contracts/",
            "ERC721A-Upgradeable/=lib/ERC721A-Upgradeable/contracts/",
            "openzeppelin-contracts-upgradeable/=lib/openzeppelin-contracts-upgradeable/",
            "openzeppelin-contracts/=lib/openzeppelin-contracts/",
            "openzeppelin/=lib/openzeppelin-contracts-upgradeable/contracts/"
          ]
        }
      },
      "imports": [
        "./EditionsStructs.sol",
        "./EditionsRoles.sol"
      ],
      "versionPragmas": [
        "^0.8.13"
      ],
      "artifacts": [
        "IEditions"
      ]
    },
    "/Users/marcuspang/Desktop/Personal/radar-contracts/src/Editions/EditionsRoles.sol": {
      "lastModificationDate": 1696080701122,
      "contentHash": "d4ae132dfd9f73b12feccb232c64c07b",
      "sourceName": "src/Editions/EditionsRoles.sol",
      "solcConfig": {
        "version": "0.8.19",
        "settings": {
          "optimizer": {
            "enabled": true,
            "runs": 200
          },
          "outputSelection": {
            "*": {
              "*": [
                "abi",
                "evm.bytecode",
                "evm.deployedBytecode",
                "evm.methodIdentifiers",
                "metadata",
                "storageLayout"
              ],
              "": [
                "ast"
              ]
            }
          },
          "remappings": [
            "ds-test/=lib/forge-std/lib/ds-test/src/",
            "erc4626-tests/=lib/openzeppelin-contracts/lib/erc4626-tests/",
            "forge-std/=lib/forge-std/src/",
            "@openzeppelin/contracts-upgradeable/=lib/openzeppelin-contracts-upgradeable/contracts/",
            "@openzeppelin/contracts/=lib/openzeppelin-contracts/contracts/",
            "ERC721A-Upgradeable/=lib/ERC721A-Upgradeable/contracts/",
            "openzeppelin-contracts-upgradeable/=lib/openzeppelin-contracts-upgradeable/",
            "openzeppelin-contracts/=lib/openzeppelin-contracts/",
            "openzeppelin/=lib/openzeppelin-contracts-upgradeable/contracts/"
          ]
        }
      },
      "imports": [],
      "versionPragmas": [
        "^0.8.13"
      ],
      "artifacts": [
        "EditionsRoles"
      ]
    },
    "/Users/marcuspang/Desktop/Personal/radar-contracts/src/Editions/EditionsStructs.sol": {
      "lastModificationDate": 1696546803510,
      "contentHash": "7b531289837057a3c40437ade3337dfb",
      "sourceName": "src/Editions/EditionsStructs.sol",
      "solcConfig": {
        "version": "0.8.19",
        "settings": {
          "optimizer": {
            "enabled": true,
            "runs": 200
          },
          "outputSelection": {
            "*": {
              "*": [
                "abi",
                "evm.bytecode",
                "evm.deployedBytecode",
                "evm.methodIdentifiers",
                "metadata",
                "storageLayout"
              ],
              "": [
                "ast"
              ]
            }
          },
          "remappings": [
            "ds-test/=lib/forge-std/lib/ds-test/src/",
            "erc4626-tests/=lib/openzeppelin-contracts/lib/erc4626-tests/",
            "forge-std/=lib/forge-std/src/",
            "@openzeppelin/contracts-upgradeable/=lib/openzeppelin-contracts-upgradeable/contracts/",
            "@openzeppelin/contracts/=lib/openzeppelin-contracts/contracts/",
            "ERC721A-Upgradeable/=lib/ERC721A-Upgradeable/contracts/",
            "openzeppelin-contracts-upgradeable/=lib/openzeppelin-contracts-upgradeable/",
            "openzeppelin-contracts/=lib/openzeppelin-contracts/",
            "openzeppelin/=lib/openzeppelin-contracts-upgradeable/contracts/"
          ]
        }
      },
      "imports": [],
      "versionPragmas": [
        "^0.8.13"
      ],
      "artifacts": [
        "EditionsStructs"
      ]
    },
    "/Users/marcuspang/Desktop/Personal/radar-contracts/src/Beliefs/IBeliefs.sol": {
      "lastModificationDate": 1697091232734,
      "contentHash": "c28bfc1a589b31868ed49fdebc00bc65",
      "sourceName": "src/Beliefs/IBeliefs.sol",
      "solcConfig": {
        "version": "0.8.19",
        "settings": {
          "optimizer": {
            "enabled": true,
            "runs": 200
          },
          "outputSelection": {
            "*": {
              "*": [
                "abi",
                "evm.bytecode",
                "evm.deployedBytecode",
                "evm.methodIdentifiers",
                "metadata",
                "storageLayout"
              ],
              "": [
                "ast"
              ]
            }
          },
          "remappings": [
            "ds-test/=lib/forge-std/lib/ds-test/src/",
            "erc4626-tests/=lib/openzeppelin-contracts/lib/erc4626-tests/",
            "forge-std/=lib/forge-std/src/",
            "@openzeppelin/contracts-upgradeable/=lib/openzeppelin-contracts-upgradeable/contracts/",
            "@openzeppelin/contracts/=lib/openzeppelin-contracts/contracts/",
            "ERC721A-Upgradeable/=lib/ERC721A-Upgradeable/contracts/",
            "openzeppelin-contracts-upgradeable/=lib/openzeppelin-contracts-upgradeable/",
            "openzeppelin-contracts/=lib/openzeppelin-contracts/",
            "openzeppelin/=lib/openzeppelin-contracts-upgradeable/contracts/"
          ]
        }
      },
      "imports": [
        "@openzeppelin/contracts/utils/structs/BitMaps.sol"
      ],
      "versionPragmas": [
        "^0.8.13"
      ],
      "artifacts": [
        "IBeliefs"
      ]
    },
    "/Users/marcuspang/Desktop/Personal/radar-contracts/src/Beliefs/Beliefs.sol": {
      "lastModificationDate": 1697818426242,
      "contentHash": "01c6ef1b8ff2ef31709345a60430a6b0",
      "sourceName": "src/Beliefs/Beliefs.sol",
      "solcConfig": {
        "version": "0.8.19",
        "settings": {
          "optimizer": {
            "enabled": true,
            "runs": 200
          },
          "outputSelection": {
            "*": {
              "*": [
                "abi",
                "evm.bytecode",
                "evm.deployedBytecode",
                "evm.methodIdentifiers",
                "metadata",
                "storageLayout"
              ],
              "": [
                "ast"
              ]
            }
          },
          "remappings": [
            "ds-test/=lib/forge-std/lib/ds-test/src/",
            "erc4626-tests/=lib/openzeppelin-contracts/lib/erc4626-tests/",
            "forge-std/=lib/forge-std/src/",
            "@openzeppelin/contracts-upgradeable/=lib/openzeppelin-contracts-upgradeable/contracts/",
            "@openzeppelin/contracts/=lib/openzeppelin-contracts/contracts/",
            "ERC721A-Upgradeable/=lib/ERC721A-Upgradeable/contracts/",
            "openzeppelin-contracts-upgradeable/=lib/openzeppelin-contracts-upgradeable/",
            "openzeppelin-contracts/=lib/openzeppelin-contracts/",
            "openzeppelin/=lib/openzeppelin-contracts-upgradeable/contracts/"
          ]
        }
      },
      "imports": [
        "@openzeppelin/contracts/utils/structs/BitMaps.sol",
        "@openzeppelin/contracts/utils/Strings.sol",
        "../Editions/Editions.sol",
        "./LibBeliefs.sol",
        "../Editions/EditionsStructs.sol",
        "./IBeliefs.sol"
      ],
      "versionPragmas": [
        "^0.8.13"
      ],
      "artifacts": [
        "Beliefs"
      ]
    },
    "/Users/marcuspang/Desktop/Personal/radar-contracts/src/Beliefs/LibBeliefs.sol": {
      "lastModificationDate": 1697091123181,
      "contentHash": "f7316b4cd577ae0b3844ab8199f2be6a",
      "sourceName": "src/Beliefs/LibBeliefs.sol",
      "solcConfig": {
        "version": "0.8.19",
        "settings": {
          "optimizer": {
            "enabled": true,
            "runs": 200
          },
          "outputSelection": {
            "*": {
              "*": [
                "abi",
                "evm.bytecode",
                "evm.deployedBytecode",
                "evm.methodIdentifiers",
                "metadata",
                "storageLayout"
              ],
              "": [
                "ast"
              ]
            }
          },
          "remappings": [
            "ds-test/=lib/forge-std/lib/ds-test/src/",
            "erc4626-tests/=lib/openzeppelin-contracts/lib/erc4626-tests/",
            "forge-std/=lib/forge-std/src/",
            "@openzeppelin/contracts-upgradeable/=lib/openzeppelin-contracts-upgradeable/contracts/",
            "@openzeppelin/contracts/=lib/openzeppelin-contracts/contracts/",
            "ERC721A-Upgradeable/=lib/ERC721A-Upgradeable/contracts/",
            "openzeppelin-contracts-upgradeable/=lib/openzeppelin-contracts-upgradeable/",
            "openzeppelin-contracts/=lib/openzeppelin-contracts/",
            "openzeppelin/=lib/openzeppelin-contracts-upgradeable/contracts/"
          ]
        }
      },
      "imports": [
        "@openzeppelin/contracts/utils/structs/BitMaps.sol",
        "@openzeppelin/contracts/utils/Strings.sol",
        "../Editions/EditionsStructs.sol",
        "./IBeliefs.sol"
      ],
      "versionPragmas": [
        "^0.8.13"
      ],
      "artifacts": [
        "LibBeliefs"
      ]
    },
    "/Users/marcuspang/Desktop/Personal/radar-contracts/node_modules/hardhat/console.sol": {
      "lastModificationDate": 1696085146650,
      "contentHash": "e2884fb4e1ef4b4a7c7ac3a227880b0f",
      "sourceName": "hardhat/console.sol",
      "solcConfig": {
        "version": "0.8.19",
        "settings": {
          "optimizer": {
            "enabled": true,
            "runs": 200
          },
          "outputSelection": {
            "*": {
              "*": [
                "abi",
                "evm.bytecode",
                "evm.deployedBytecode",
                "evm.methodIdentifiers",
                "metadata",
                "storageLayout"
              ],
              "": [
                "ast"
              ]
            }
          },
          "remappings": [
            "ds-test/=lib/forge-std/lib/ds-test/src/",
            "erc4626-tests/=lib/openzeppelin-contracts/lib/erc4626-tests/",
            "forge-std/=lib/forge-std/src/",
            "@openzeppelin/contracts-upgradeable/=lib/openzeppelin-contracts-upgradeable/contracts/",
            "@openzeppelin/contracts/=lib/openzeppelin-contracts/contracts/",
            "ERC721A-Upgradeable/=lib/ERC721A-Upgradeable/contracts/",
            "openzeppelin-contracts-upgradeable/=lib/openzeppelin-contracts-upgradeable/",
            "openzeppelin-contracts/=lib/openzeppelin-contracts/",
            "openzeppelin/=lib/openzeppelin-contracts-upgradeable/contracts/"
          ]
        }
      },
      "imports": [],
      "versionPragmas": [
        ">= 0.4.22 <0.9.0"
      ],
      "artifacts": [
        "console"
      ]
    }
  }
}
